ulula/__init__.py
ulula/core/__init__.py
ulula/core/plots.py
ulula/core/run.py
ulula/core/setup_base.py
ulula/core/simulation.py
ulula/examples/__init__.py
ulula/examples/examples.py
ulula/physics/__init__.py
ulula/physics/constants.py
ulula/physics/units.py
ulula/setups/__init__.py
ulula/setups/advection_1d.py
ulula/setups/advection_2d.py
ulula/setups/atmosphere.py
ulula/setups/cloud_crushing.py
ulula/setups/freefall.py
ulula/setups/gresho_vortex.py
ulula/setups/jeans_instability.py
ulula/setups/kelvin_helmholtz.py
ulula/setups/keplerian_disk.py
ulula/setups/merger.py
ulula/setups/rayleigh_taylor.py
ulula/setups/sedov_taylor.py
ulula/setups/shocktube.py
ulula/setups/soundwave.py
ulula/setups/tidal_disruption.py
ulula/utils/__init__.py
ulula/utils/utils.py
ulula/utils/version.py
ulula-1.0.1.dist-info/licenses/LICENSE.txt
ulula-1.0.1.dist-info/METADATA
ulula-1.0.1.dist-info/WHEEL
ulula-1.0.1.dist-info/top_level.txt
ulula-1.0.1.dist-info/RECORD
